setup.py
confeitaria/__init__.py
confeitaria/__main__.py
confeitaria/interfaces.py
confeitaria/request.py
confeitaria/responses.py
confeitaria/runner.py
confeitaria.egg-info/PKG-INFO
confeitaria.egg-info/SOURCES.txt
confeitaria.egg-info/dependency_links.txt
confeitaria.egg-info/top_level.txt
confeitaria/server/__init__.py
confeitaria/server/environment.py
confeitaria/server/requestparser.py
confeitaria/server/server.py
confeitaria/server/session.py
confeitaria_tests/__init__.py
confeitaria_tests/interfaces.py
confeitaria_tests/reference.py
confeitaria_tests/responses.py
confeitaria_tests/server/__init__.py
confeitaria_tests/server/__main__.py
confeitaria_tests/server/environment.py
confeitaria_tests/server/requestparser.py
confeitaria_tests/server/server.py
confeitaria_tests/server/session.py