Metadata-Version: 1.0
Name: confeitaria
Version: 0.1a3
Summary: Confeitaria is a Python web framework
Home-page: http://bitbucket.com/brandizzi/confeitaria
Author: Adam Victor Brandizzi
Author-email: adam@brandizzi.com.br
License: LGPLv3
Platform: UNKNOWN
